penne/__init__.py
penne/core.py
penne/delegates.py
penne/handlers.py
penne-0.5.5.dist-info/WHEEL
penne-0.5.5.dist-info/METADATA
penne-0.5.5.dist-info/RECORD
