Metadata-Version: 2.1
Name: penne
Version: 0.5.5
Summary: Python Client Library for NOODLES Protocol
Keywords: noodles,cbor,Websockets,client,NOODLES
Author: Alex Racapé
Requires-Python: >=3.9
Classifier: Intended Audience :: Science/Research
Classifier: Programming Language :: Python :: 3
Classifier: Topic :: Scientific/Engineering :: Visualization
Requires-Dist: websockets==11.0.3
Requires-Dist: cbor2==5.4.6
Requires-Dist: pydantic==2.1.1
Requires-Dist: pydantic-extra-types==2.0.0
Requires-Dist: pytest ; extra == "testing"
Requires-Dist: rigatoni ; extra == "testing"
Requires-Dist: pandas ; extra == "testing"
Requires-Dist: matplotlib ; extra == "testing"
Project-URL: Documentation, https://insightcenternoodles.github.io/Penne/
Project-URL: Source, https://github.com/InsightCenterNoodles/Penne
Provides-Extra: testing
